odoo9_addon_support_branding-9.0.2.0.0.99.dev5-py2.7-nspkg.pth
odoo9_addon_support_branding-9.0.2.0.0.99.dev5.dist-info/DESCRIPTION.rst
odoo9_addon_support_branding-9.0.2.0.0.99.dev5.dist-info/METADATA
odoo9_addon_support_branding-9.0.2.0.0.99.dev5.dist-info/RECORD
odoo9_addon_support_branding-9.0.2.0.0.99.dev5.dist-info/WHEEL
odoo9_addon_support_branding-9.0.2.0.0.99.dev5.dist-info/metadata.json
odoo9_addon_support_branding-9.0.2.0.0.99.dev5.dist-info/namespace_packages.txt
odoo9_addon_support_branding-9.0.2.0.0.99.dev5.dist-info/top_level.txt
odoo_addons/support_branding/README.rst
odoo_addons/support_branding/__init__.py
odoo_addons/support_branding/__openerp__.py
odoo_addons/support_branding/data/ir_config_parameter.xml
odoo_addons/support_branding/i18n/ar.po
odoo_addons/support_branding/i18n/de.po
odoo_addons/support_branding/i18n/es.po
odoo_addons/support_branding/i18n/fi.po
odoo_addons/support_branding/i18n/fr.po
odoo_addons/support_branding/i18n/it.po
odoo_addons/support_branding/i18n/nl.po
odoo_addons/support_branding/i18n/pt_BR.po
odoo_addons/support_branding/i18n/pt_PT.po
odoo_addons/support_branding/i18n/sl.po
odoo_addons/support_branding/i18n/tr.po
odoo_addons/support_branding/static/description/icon.png
odoo_addons/support_branding/static/src/css/support_branding.css
odoo_addons/support_branding/static/src/js/support_branding.js
odoo_addons/support_branding/static/src/xml/base.xml
odoo_addons/support_branding/views/qweb.xml
