Metadata-Version: 2.0
Name: odoo9-addon-support-branding
Version: 9.0.2.0.0.99.dev5
Summary: Adds your branding to an Odoo instance
Home-page: http://therp.nl
Author: Therp BV,Tecnativa,Odoo Community Association (OCA)
Author-email: support@odoo-community.org
License: AGPL-3
Platform: UNKNOWN
Classifier: Programming Language :: Python
Classifier: Framework :: Odoo
Classifier: License :: OSI Approved :: GNU Affero General Public License v3
Requires-Python: ~=2.7
Requires-Dist: odoo (<9.1a,>=9.0a)
